<splits>
  <work>
    <name>T0278-paralleled-earlier</name>
    <parts>
      <part>
        <witnesses>大,宋,元,明,聖,CB,北藏-CB,南藏,知,磧-CB</witnesses>
        <start>佛在摩竭提國寂滅道場，初始得佛，普光法</start>
        <end>最勝，或稱能度。如是等稱佛名號，其數一
萬</end>
      </part>
      <part>
        <witnesses>宮</witnesses>
        <start>佛在摩竭提國寂滅道場，初始得佛，普光法</start>
        <end>最勝，或稱能度。如是稱佛名號，其數一
萬</end>
      </part>
      <part>
        <witnesses>ALL</witnesses>
        <start>爾時，世尊從兩足相輪放百億光明，遍照</start>
        <end>百億色究竟天，此世
界所有一切悉現</end>
      </part>
      <part>
        <witnesses>ALL</witnesses>
        <start>爾時，智首菩薩問文殊師利言：「佛子！云何</start>
        <end>覺，   不捨十方</end>
      </part>
      <part>
        <witnesses>宋,元,明,宮,CB,北藏-CB,南藏,宮,知,磧-CB</witnesses>
        <start>爾時，如來威神力故，十方一切諸佛世界諸
四天下，一一閻浮提，皆有如來坐菩提樹
下，無不顯現。彼諸菩薩各承佛神力，說種
種法。皆悉自謂：在於佛所。
爾時，世尊威神
力故，不起</start>
        <end>昇妙勝殿；一切十方亦
復如是</end>
      </part>
      <part>
        <witnesses>大</witnesses>
        <start>爾時，如來威神力故，十方一切諸物世界諸
四天下，一一閻浮提，皆有如來坐菩提樹
下，無不顯現。彼諸菩薩各承佛神力，說種
種法。皆悉自謂：在於佛所。
爾時，世尊威神
力故，不起</start>
        <end>昇妙勝殿；一切十方亦
復如是</end>
      </part>
      <part>
        <witnesses>聖</witnesses>
        <start>爾時，如來威神力故，十方一切諸佛世界諸
四天下，一一閻浮提，皆有如來坐菩提樹
下，無不顯現。彼諸菩薩各承佛神力，說種
種法。皆悉自謂：在於佛前。
爾時，世尊威神
力故，不起</start>
        <end>昇妙勝殿；一切十方亦
復如是</end>
      </part>
      <part>
        <witnesses>ALL</witnesses>
        <start>爾時，十方各過百佛世界微塵數剎，一一方</start>
        <end>詣佛所，恭敬禮拜。又佛神力故，化作寶藏師
子之座，結跏趺坐，充滿十方</end>
      </part>
      <part>
        <witnesses>ALL</witnesses>
        <start>爾時，法慧菩薩承佛神力，入菩薩無量方便</start>
        <end>以故？欲令具足一切種智，有所聞法，即自
開解，不由他悟</end>
      </part>
    </parts>
  </work>
  <work>
    <name>T0278-ex-earlier-parallels</name>
    <parts>
      <part>
        <witnesses>ALL</witnesses>
        <start>如是我聞：
一時，佛在摩竭提國寂滅道場始</start>
        <end>入一切法
方便海三昧</end>
      </part>
      <part>
        <witnesses>ALL</witnesses>
        <start>諸佛子！次此東方有四天下，名曰善護</start>
        <end>作如是說。南、西、北方，四維，上、下，亦
復如是</end>
      </part>
      <part>
        <witnesses>ALL</witnesses>
        <start>如此見佛坐蓮華藏師子
座上，有十佛世界塵數菩薩眷屬圍遶，百億
閻浮提亦復如是</start>
        <end>見；南、西、北方，四維，上、下，亦復如是</end>
      </part>
      <part>
        <witnesses>ALL</witnesses>
        <start>佛子！是為菩薩身、口、意業能得一切勝妙功</start>
        <end>善哉善哉真佛子，   快說是法我隨喜</end>
      </part>
      <part>
        <witnesses>ALL</witnesses>
        <start>爾時，帝釋無量樂音，佛神力故，寂然</start>
        <end>忉利天處，一切十方，亦復如是</end>
      </part>
      <part>
        <witnesses>ALL</witnesses>
        <start>如此世界須彌
山頂，菩薩雲集</start>
        <end>無數億劫中，   說佛德無盡</end>
      </part>
      <part>
        <witnesses>ALL</witnesses>
        <start>爾時，佛神力故，十方各萬佛世界塵數佛國</start>
        <end>速成無上道，   與諸如來等</end>
      </part>
    </parts>
  </work>
</splits>
